cdktf_cdktf_provider_pagerduty/__init__.py
cdktf_cdktf_provider_pagerduty/py.typed
cdktf_cdktf_provider_pagerduty/_jsii/__init__.py
cdktf_cdktf_provider_pagerduty/_jsii/provider-pagerduty@14.3.5.jsii.tgz
cdktf_cdktf_provider_pagerduty/addon/__init__.py
cdktf_cdktf_provider_pagerduty/alert_grouping_setting/__init__.py
cdktf_cdktf_provider_pagerduty/automation_actions_action/__init__.py
cdktf_cdktf_provider_pagerduty/automation_actions_action_service_association/__init__.py
cdktf_cdktf_provider_pagerduty/automation_actions_action_team_association/__init__.py
cdktf_cdktf_provider_pagerduty/automation_actions_runner/__init__.py
cdktf_cdktf_provider_pagerduty/automation_actions_runner_team_association/__init__.py
cdktf_cdktf_provider_pagerduty/business_service/__init__.py
cdktf_cdktf_provider_pagerduty/business_service_subscriber/__init__.py
cdktf_cdktf_provider_pagerduty/data_pagerduty_alert_grouping_setting/__init__.py
cdktf_cdktf_provider_pagerduty/data_pagerduty_automation_actions_action/__init__.py
cdktf_cdktf_provider_pagerduty/data_pagerduty_automation_actions_runner/__init__.py
cdktf_cdktf_provider_pagerduty/data_pagerduty_business_service/__init__.py
cdktf_cdktf_provider_pagerduty/data_pagerduty_escalation_policy/__init__.py
cdktf_cdktf_provider_pagerduty/data_pagerduty_event_orchestration/__init__.py
cdktf_cdktf_provider_pagerduty/data_pagerduty_event_orchestration_global_cache_variable/__init__.py
cdktf_cdktf_provider_pagerduty/data_pagerduty_event_orchestration_integration/__init__.py
cdktf_cdktf_provider_pagerduty/data_pagerduty_event_orchestration_service_cache_variable/__init__.py
cdktf_cdktf_provider_pagerduty/data_pagerduty_event_orchestrations/__init__.py
cdktf_cdktf_provider_pagerduty/data_pagerduty_extension_schema/__init__.py
cdktf_cdktf_provider_pagerduty/data_pagerduty_incident_custom_field/__init__.py
cdktf_cdktf_provider_pagerduty/data_pagerduty_incident_type/__init__.py
cdktf_cdktf_provider_pagerduty-14.3.5.dist-info/LICENSE
cdktf_cdktf_provider_pagerduty-14.3.5.dist-info/METADATA
cdktf_cdktf_provider_pagerduty-14.3.5.dist-info/WHEEL
cdktf_cdktf_provider_pagerduty-14.3.5.dist-info/top_level.txt
cdktf_cdktf_provider_pagerduty-14.3.5.dist-info/RECORD
